riskfolioxl/__init__.cp39-win_amd64.pyd
riskfolioxl/data.cp39-win_amd64.pyd
riskfolioxl/optimize.cp39-win_amd64.pyd
riskfolioxl/params.cp39-win_amd64.pyd
riskfolioxl/plot.cp39-win_amd64.pyd
riskfolioxl/pyxll.cp39-win_amd64.pyd
riskfolioxl/risk.cp39-win_amd64.pyd
riskfolioxl/version.cp39-win_amd64.pyd
riskfolioxl/examples/01_data.xlsx
riskfolioxl/examples/02_risk.xlsx
riskfolioxl/examples/03_plots.xlsx
riskfolioxl/examples/04_params.xlsx
riskfolioxl/examples/05_optimize_classic.xlsx
riskfolioxl/examples/06_optimize_frontier.xlsx
riskfolioxl/examples/07_optimize_factors.xlsx
riskfolioxl/examples/08_optimize_bl.xlsx
riskfolioxl/examples/09_optimize_bl_fm.xlsx
riskfolioxl/examples/10_optimize_rp.xlsx
riskfolioxl/examples/11_optimize_hc.xlsx
riskfolioxl/examples/12_optimize_network.xlsx
riskfolioxl/ribbon/__init__.cp39-win_amd64.pyd
riskfolioxl/ribbon/ribbon.xml
riskfolioxl/ribbon/icons/about.png
riskfolioxl/ribbon/icons/docs.png
riskfolioxl/ribbon/icons/documents.ico
riskfolioxl/ribbon/icons/files.ico
riskfolioxl/ribbon/icons/log.png
riskfolioxl/ribbon/icons/reload.png
Riskfolio_XL-0.1.1.dist-info/LICENSE.txt
Riskfolio_XL-0.1.1.dist-info/METADATA
Riskfolio_XL-0.1.1.dist-info/WHEEL
Riskfolio_XL-0.1.1.dist-info/entry_points.txt
Riskfolio_XL-0.1.1.dist-info/top_level.txt
Riskfolio_XL-0.1.1.dist-info/RECORD
