Metadata-Version: 2.1
Name: Riskfolio-XL
Version: 0.1.1
Summary: Riskfolio-Lib add-in for Microsoft Excel
Home-page: https://riskfolio-lib.readthedocs.io/en/latest/excel.html
Download-URL: https://pypi.org/project/Riskfolio-XL/
Author: Dany Cajas
Author-email: dany.cajas.n@uni.pe
Maintainer: Dany Cajas
Maintainer-email: dany.cajas.n@uni.pe
License: Other/Proprietary License (Other/Proprietary License)
Keywords: finance,portfolio,optimization,quant,asset,allocation,investing
Classifier: Intended Audience :: Financial and Insurance Industry
Classifier: Intended Audience :: Science/Research
Classifier: Programming Language :: Python :: 3.9
Classifier: Programming Language :: Python :: 3.10
Classifier: Programming Language :: Python :: 3.11
Classifier: Programming Language :: Python :: 3.12
Classifier: Topic :: Office/Business :: Financial :: Investment
Classifier: Topic :: Office/Business :: Financial
Classifier: Topic :: Scientific/Engineering :: Mathematics
Classifier: Operating System :: Microsoft
Requires-Python: >=3.9
License-File: LICENSE.txt
Requires-Dist: numpy>=1.24.0
Requires-Dist: scipy>=1.10.0
Requires-Dist: pandas>=2.0.0
Requires-Dist: matplotlib>=3.8.0
Requires-Dist: clarabel>=0.6.0
Requires-Dist: cvxpy>=1.5.2
Requires-Dist: scikit-learn>=1.3.0
Requires-Dist: statsmodels>=0.13.5
Requires-Dist: arch>=7.0
Requires-Dist: xlsxwriter>=3.1.2
Requires-Dist: networkx>=3.0
Requires-Dist: astropy>=5.1
Requires-Dist: pybind11>=2.10.1
Requires-Dist: yfinance>=0.2.43
Requires-Dist: pyxll>=5.9.1
Requires-Dist: requests>=2.31.0
Requires-Dist: cryptography>=43.0.1
Requires-Dist: pyopenssl>=24.2.1
Requires-Dist: py-machineid>=0.6.0
Requires-Dist: riskfolio-lib>=6.3.1
Requires-Dist: cython>=3.0.11
